[{"id":"69cf9b40bd732","message":"[12:49] hath has added a new record to OperationsPayments","timestamp":1775213376,"read":false},{"id":"69cf98a8239ca","message":"[12:38] hath has added a new record to OperationsPayments","timestamp":1775212712,"read":false},{"id":"69cf988056395","message":"[12:37] hath has added a new record to OperationsPayments","timestamp":1775212672,"read":false},{"id":"69cf79b03963d","message":"[10:26] hath has added a new record to OperationsPayments","timestamp":1775204784,"read":false},{"id":"69cf292f55e6e","message":"[04:42] hath has added a new record to OperationsPayments","timestamp":1775184175,"read":false},{"id":"69cf28d95f1a4","message":"[04:41] hath has added a new record to OperationsPayments","timestamp":1775184089,"read":false},{"id":"69cf27dccbaee","message":"[04:37] hath has added a new record to OperationsPayments","timestamp":1775183836,"read":false},{"id":"69cf266011a13","message":"[04:30] hath has added a new record to OperationsPayments","timestamp":1775183456,"read":false},{"id":"69cf2647bb395","message":"[04:30] hath has added a new record to OperationsPayments","timestamp":1775183431,"read":false},{"id":"69cf263965b4c","message":"[04:30] hath has added a new record to OperationsPayments","timestamp":1775183417,"read":false},{"id":"69cf25e45d786","message":"[04:28] Test System has added a new record to Operations","timestamp":1775183332,"read":false},{"id":"69cf255559044","message":"[04:26] hath has added a new record to OperationsPayments","timestamp":1775183189,"read":false},{"id":"69cf252c8f886","message":"[04:25] hath has added a new record to OperationsPayments","timestamp":1775183148,"read":false},{"id":"69cf22e6ac57b","message":"[04:16] hath has added a new record to OperationsPayments","timestamp":1775182566,"read":false},{"id":"69cf22d2c9b80","message":"[04:15] hath has added a new record to OperationsPayments","timestamp":1775182546,"read":false},{"id":"69cf22bf0d89c","message":"[04:15] hath has added a new record to OperationsPayments","timestamp":1775182527,"read":false},{"id":"69cf22aabff64","message":"[04:15] hath has added a new record to OperationsPayments","timestamp":1775182506,"read":false},{"id":"69cf22a0ea409","message":"[04:14] hath has added a new record to OperationsPayments","timestamp":1775182496,"read":false},{"id":"69cf229a66d13","message":"[04:14] hath has added a new record to OperationsPayments","timestamp":1775182490,"read":false},{"id":"69cf227137826","message":"[04:14] hath has added a new record to OperationsPayments","timestamp":1775182449,"read":false}]